nonebot_plugin_apexranklookup/__init__.py
nonebot_plugin_apexranklookup/api.py
nonebot_plugin_apexranklookup/config.py
nonebot_plugin_apexranklookup/data/font/SourceHanSansCN-Normal.ttf
nonebot_plugin_apexranklookup/data/image/base.png
nonebot_plugin_apexranklookup/data/user_info.json
nonebot_plugin_apexranklookup/draw.py
nonebot_plugin_apexranklookup/zh_cn.json
nonebot_plugin_apexranklookup-0.1.7.dist-info/METADATA
nonebot_plugin_apexranklookup-0.1.7.dist-info/WHEEL
nonebot_plugin_apexranklookup-0.1.7.dist-info/RECORD
