Metadata-Version: 2.1
Name: nonebot-plugin-apexranklookup
Version: 0.1.7
Summary: 
Author: Windylh
Requires-Python: >=3.8,<4.0
Classifier: Programming Language :: Python :: 3
Classifier: Programming Language :: Python :: 3.8
Classifier: Programming Language :: Python :: 3.9
Classifier: Programming Language :: Python :: 3.10
Classifier: Programming Language :: Python :: 3.11
Requires-Dist: Pillow (>=9.4.0,<10.0.0)
Requires-Dist: loguru (>=0.6.0,<0.7.0)
Requires-Dist: nonebot-adapter-onebot (>=2.2.1,<3.0.0)
Requires-Dist: nonebot2 (>=2.0.0rc3,<3.0.0)
Requires-Dist: pydantic (>=1.10.6,<2.0.0)
Requires-Dist: requests (>=2.28.2,<3.0.0)
